[
  {
    "business_name": "Jumbo Supermarket",
    "sector": "Supermarkets",
    "followers_count": 5532,
    "post_date": "2026-05-10",
    "posting_hour": null,
    "day_of_week": "Sunday",
    "month": "May",
    "post_type": "reel",
    "caption_text": "اربح مع نايس 💵😍",
    "caption_length": 18,
    "hashtags_count": 0,
    "emoji_count": 2,
    "likes_count": 27,
    "comments_count": null,
    "views_count": 4333,
    "language": "Arabic",
    "CTA_present": true,
    "promo_post": true,
    "discount_percent": null,
    "mentions_location": false,
    "religious_theme": false,
    "patriotic_theme": false,
    "arabic_dialect_style": true,
    "sponsored": false
  },
  {
    "business_name": "Jumbo Supermarket",
    "sector": "Supermarkets",
    "followers_count": 5532,
    "post_date": "2026-05-08",
    "posting_hour": null,
    "day_of_week": "Friday",
    "month": "May",
    "post_type": "reel",
    "caption_text": "الطازة عنا عنوان، والنظافة عنا أساس 🐔👌 دجاج فرش كل يوم بيومه 🔥",
    "caption_length": 68,
    "hashtags_count": 0,
    "emoji_count": 3,
    "likes_count": 28,
    "comments_count": 1,
    "views_count": 2674,
    "language": "Arabic",
    "CTA_present": false,
    "promo_post": true,
    "discount_percent": null,
    "mentions_location": false,
    "religious_theme": false,
    "patriotic_theme": false,
    "arabic_dialect_style": true,
    "sponsored": false
  },
  {
    "business_name": "Jumbo Supermarket",
    "sector": "Supermarkets",
    "followers_count": 5532,
    "post_date": "2026-05-06",
    "posting_hour": null,
    "day_of_week": "Wednesday",
    "month": "May",
    "post_type": "reel",
    "caption_text": "🔥حمسنا شغلة الآن🔥 الكوتي متوفر عندنا، وفكرة السحب غير 😍 اشتري كيس كوتي 🛒 وافتحه فوراً ورتب حظك، لأنو في كيس واحد فيه الجائزة 🎁🎉 يمكن انت تكون الرابح.",
    "caption_length": 154,
    "hashtags_count": 0,
    "emoji_count": 8,
    "likes_count": 9,
    "comments_count": null,
    "views_count": 1953,
    "language": "Arabic",
    "CTA_present": true,
    "promo_post": true,
    "discount_percent": null,
    "mentions_location": false,
    "religious_theme": false,
    "patriotic_theme": false,
    "arabic_dialect_style": true,
    "sponsored": false
  },
  {
    "business_name": "Jumbo Supermarket",
    "sector": "Supermarkets",
    "followers_count": 5532,
    "post_date": "2026-04-30",
    "posting_hour": null,
    "day_of_week": "Thursday",
    "month": "April",
    "post_type": "reel",
    "caption_text": "✨🛡💪 اختاري المكان والتعقيم على StarX #لنظافة_المنزل #تعقيم #ثقة #جمالية starx",
    "caption_length": 85,
    "hashtags_count": 4,
    "emoji_count": 3,
    "likes_count": 7,
    "comments_count": 2,
    "views_count": 1531,
    "language": "Arabic",
    "CTA_present": false,
    "promo_post": true,
    "discount_percent": null,
    "mentions_location": false,
    "religious_theme": false,
    "patriotic_theme": false,
    "arabic_dialect_style": true,
    "sponsored": false
  },
  {
    "business_name": "Jumbo Supermarket",
    "sector": "Supermarkets",
    "followers_count": 5532,
    "post_date": "2026-04-28",
    "posting_hour": null,
    "day_of_week": "Tuesday",
    "month": "April",
    "post_type": "reel",
    "caption_text": "🆕🚛 ال UNBOXING على مستوى ثاني شو بتتوقعوا وصل عالجمبو؟📦 شاركونا توقعاتكم بالكومنتس 👇 الجواب قريب!",
    "caption_length": 102,
    "hashtags_count": 0,
    "emoji_count": 5,
    "likes_count": 65,
    "comments_count": 9,
    "views_count": 9610,
    "language": "Arabic",
    "CTA_present": true,
    "promo_post": false,
    "discount_percent": null,
    "mentions_location": false,
    "religious_theme": false,
    "patriotic_theme": false,
    "arabic_dialect_style": true,
    "sponsored": false
  },
  {
    "business_name": "Jumbo Supermarket",
    "sector": "Supermarkets",
    "followers_count": 5532,
    "post_date": "2026-04-27",
    "posting_hour": null,
    "day_of_week": "Monday",
    "month": "April",
    "post_type": "reel",
    "caption_text": "🔥 جاهزين للجديد؟ لأنه اللي جاي غير 🆕 Are you ready? Because what’s coming is different",
    "caption_length": 94,
    "hashtags_count": 0,
    "emoji_count": 2,
    "likes_count": 52,
    "comments_count": 7,
    "views_count": 5828,
    "language": "Mixed",
    "CTA_present": true,
    "promo_post": false,
    "discount_percent": null,
    "mentions_location": false,
    "religious_theme": false,
    "patriotic_theme": false,
    "arabic_dialect_style": true,
    "sponsored": false
  },
  {
    "business_name": "Jumbo Supermarket",
    "sector": "Supermarkets",
    "followers_count": 5532,
    "post_date": "2026-04-16",
    "posting_hour": null,
    "day_of_week": "Thursday",
    "month": "April",
    "post_type": "reel",
    "caption_text": "🎉 اليوم عنا فعالية مميزة 💜 تعالوا على السوبرماركت وخلو أطفالكم يعيشوا أجواء بارني 🧸 اللعب والمرح ويمكن تكونوا من الفائزين اليوم! لا تفوتوا الفرصة اليوم! nedm.palestine@",
    "caption_length": 168,
    "hashtags_count": 0,
    "emoji_count": 4,
    "likes_count": 40,
    "comments_count": 1,
    "views_count": 6535,
    "language": "Arabic",
    "CTA_present": true,
    "promo_post": true,
    "discount_percent": null,
    "mentions_location": false,
    "religious_theme": false,
    "patriotic_theme": false,
    "arabic_dialect_style": true,
    "sponsored": false
  },
  {
    "business_name": "Jumbo Supermarket",
    "sector": "Supermarkets",
    "followers_count": 5532,
    "post_date": "2026-04-07",
    "posting_hour": null,
    "day_of_week": "Tuesday",
    "month": "April",
    "post_type": "reel",
    "caption_text": "أطلقت شركة مرح حملة تواليت لولو 🎉🔥 اشتري تواليت لولو واحصل على محارم مجاناً وتسوقوا وادخلوا السحب لفرصة ربح $100 ✨ مؤسسة مرح الاستهلاكية",
    "caption_length": 145,
    "hashtags_count": 0,
    "emoji_count": 5,
    "likes_count": 40,
    "comments_count": 1,
    "views_count": 6406,
    "language": "Arabic",
    "CTA_present": true,
    "promo_post": true,
    "discount_percent": null,
    "mentions_location": false,
    "religious_theme": false,
    "patriotic_theme": false,
    "arabic_dialect_style": true,
    "sponsored": false
  },
  {
    "business_name": "Jumbo Supermarket",
    "sector": "Supermarkets",
    "followers_count": 5532,
    "post_date": "2026-03-18",
    "posting_hour": null,
    "day_of_week": "Wednesday",
    "month": "March",
    "post_type": "reel",
    "caption_text": "من قسم الخضار... جهزنا العيد على أصوله 🍍🍎",
    "caption_length": 45,
    "hashtags_count": 0,
    "emoji_count": 2,
    "likes_count": 20,
    "comments_count": 1,
    "views_count": 4533,
    "language": "Arabic",
    "CTA_present": false,
    "promo_post": true,
    "discount_percent": null,
    "mentions_location": false,
    "religious_theme": true,
    "patriotic_theme": false,
    "arabic_dialect_style": true,
    "sponsored": false
  },
  {
    "business_name": "Jumbo Supermarket",
    "sector": "Supermarkets",
    "followers_count": 5532,
    "post_date": "2026-03-17",
    "posting_hour": null,
    "day_of_week": "Tuesday",
    "month": "March",
    "post_type": "reel",
    "caption_text": "ختمنا حماسنا الرمضانية مع شركة ايكا... والحماس لسا مكمل 🔥🎉 الأجواء كانت ولا أروع والفعاليات كانت مليانة حماس 🤩 بس لسا في مفاجآت! حط كومنت على البوست وممكن تكون إنت الرابح بجائزة مميزة من ايكا 🎁 #رمضان #فعاليات #جوائز #عروض #jumbo",
    "caption_length": 271,
    "hashtags_count": 5,
    "emoji_count": 8,
    "likes_count": 129,
    "comments_count": 34,
    "views_count": 13400,
    "language": "Arabic",
    "CTA_present": true,
    "promo_post": true,
    "discount_percent": null,
    "mentions_location": false,
    "religious_theme": true,
    "patriotic_theme": false,
    "arabic_dialect_style": true,
    "sponsored": false
  },
  {
    "business_name": "Jumbo Supermarket",
    "sector": "Supermarkets",
    "followers_count": 5532,
    "post_date": "2026-03-16",
    "posting_hour": null,
    "day_of_week": "Monday",
    "month": "March",
    "post_type": "reel",
    "caption_text": "اليوم كملنا أجواء حملتنا الرمضانية مع شركة بلاكو 🔥😍 ومع مشروب فيدا اللي عاملين عليه عرض نار ✨🎁 اشتروا كل 4 بـ10 وادخلوا فرصة تربحوا جوائز كتير قيمة #فعاليات_رمضان #عروض #jumbo #مشروب_فيدا",
    "caption_length": 224,
    "hashtags_count": 4,
    "emoji_count": 7,
    "likes_count": 73,
    "comments_count": 5,
    "views_count": 9442,
    "language": "Arabic",
    "CTA_present": true,
    "promo_post": true,
    "discount_percent": null,
    "mentions_location": false,
    "religious_theme": true,
    "patriotic_theme": false,
    "arabic_dialect_style": true,
    "sponsored": false
  }
]
